cwmed/__init__.py
cwmed-0.1.0.dist-info/LICENSE
cwmed-0.1.0.dist-info/METADATA
cwmed-0.1.0.dist-info/WHEEL
cwmed-0.1.0.dist-info/top_level.txt
cwmed-0.1.0.dist-info/RECORD
