Metadata-Version: 2.1
Name: cwmed
Version: 0.1.0
Summary: Crosswalk Medical: crosswalk between source and target medical terminologies.
Author-email: The Laboratory for Computational Physiology <contact@physionet.org>
License: MIT License
Project-URL: Homepage, https://github.com/MIT-LCP/cwmed
Project-URL: Bug Tracker, https://github.com/MIT-LCP/cwmed
Classifier: Programming Language :: Python :: 3
Classifier: License :: OSI Approved :: MIT License
Classifier: Operating System :: OS Independent
Requires-Python: >=3.7
License-File: LICENSE
Requires-Dist: requests >=2.8.1
Requires-Dist: pandas >=1.0.0
